pyspark_mcp_server/__init__.py
pyspark_mcp_server/cli.py
pyspark_mcp_server/mcp_server.py
pyspark_mcp-0.0.4.dist-info/METADATA
pyspark_mcp-0.0.4.dist-info/WHEEL
pyspark_mcp-0.0.4.dist-info/entry_points.txt
pyspark_mcp-0.0.4.dist-info/licenses/LICENSE
pyspark_mcp-0.0.4.dist-info/RECORD
