Metadata-Version: 2.4
Name: pyspark-mcp
Version: 0.0.4
Summary: Minimal PySpark MCP server inspired by LakeSail
License-Expression: Apache-2.0
License-File: LICENSE
Keywords: pyspark,mcp,llm,ai
Author: Sem Sinchenko
Author-email: semensinchenko@gmail.com
Requires-Python: >=3.11,<4.0
Classifier: Development Status :: 4 - Beta
Classifier: License :: OSI Approved :: Apache Software License
Classifier: Operating System :: OS Independent
Classifier: Programming Language :: Python :: 3
Classifier: Programming Language :: Python :: 3.11
Classifier: Programming Language :: Python :: 3.12
Classifier: Programming Language :: Python :: 3.13
Classifier: Intended Audience :: Developers
Classifier: Topic :: Database :: Front-Ends
Requires-Dist: click (>=8.0)
Requires-Dist: fastmcp (>=2.10.6)
Requires-Dist: loguru
Requires-Dist: pandas (>=2.3.2,<3.0.0)
Requires-Dist: pyspark (>=3.5)
Project-URL: Bug Tracker, https://github.com/SemyonSinchenko/pyspark-mcp-server/issues
Project-URL: Code Repository, https://github.com/SemyonSinchenko/pyspark-mcp-server
